icenlp_bridge/__init__.py
icenlp_bridge/__main__.py
icenlp_bridge/bridge.py
icenlp_bridge-0.1.1.dist-info/AUTHORS.rst
icenlp_bridge-0.1.1.dist-info/LICENSE
icenlp_bridge-0.1.1.dist-info/METADATA
icenlp_bridge-0.1.1.dist-info/WHEEL
icenlp_bridge-0.1.1.dist-info/top_level.txt
icenlp_bridge-0.1.1.dist-info/RECORD
