Metadata-Version: 2.1
Name: icenlp-bridge
Version: 0.1.1
Summary: Simplify using IceNLP (Icelandic NLP library written in Java)
Home-page: https://github.com/sverrirab/icenlp_bridge
Author: Sverrir Á. Berg
Author-email: sab@keilir.com
License: Apache Software License 2.0
Keywords: icenlp_bridge
Platform: UNKNOWN
Classifier: Development Status :: 3 - Alpha
Classifier: Intended Audience :: Developers
Classifier: License :: OSI Approved :: Apache Software License
Classifier: Natural Language :: Icelandic
Classifier: Programming Language :: Python :: 3
Classifier: Programming Language :: Python :: 3.7
